HISTORY.rst
LICENSE.txt
MANIFEST.in
README.rst
mstranslator.py
setup.cfg
setup.py
mstranslator.egg-info/PKG-INFO
mstranslator.egg-info/SOURCES.txt
mstranslator.egg-info/dependency_links.txt
mstranslator.egg-info/requires.txt
mstranslator.egg-info/top_level.txt