Metadata-Version: 1.1
Name: mstranslator
Version: 0.2.3
Summary: Microsoft Translator API wrapper
Home-page: https://github.com/wronglink/mstranslator
Author: Michael Elovskikh
Author-email: wronglink@gmail.com
License: MIT
Platform: UNKNOWN
Classifier: Development Status :: 2 - Pre-Alpha
Classifier: Intended Audience :: Developers
Classifier: License :: OSI Approved :: MIT License
Classifier: Programming Language :: Python
Classifier: Programming Language :: Python :: 3
